portage-3.0.77.dist-info/METADATA
portage-3.0.77.dist-info/WHEEL
portage-3.0.77.dist-info/entry_points.txt
portage-3.0.77.dist-info/LICENSE
portage-3.0.77.data/data/lib/portage/bin/ebuild
portage-3.0.77.data/data/lib/portage/bin/egencache
portage-3.0.77.data/data/lib/portage/bin/emerge
portage-3.0.77.data/data/lib/portage/bin/emirrordist
portage-3.0.77.data/data/lib/portage/bin/glsa-check
portage-3.0.77.data/data/lib/portage/bin/gpkg-sign
portage-3.0.77.data/data/lib/portage/bin/portageq
portage-3.0.77.data/data/lib/portage/bin/quickpkg
portage-3.0.77.data/data/lib/portage/bin/archive-conf
portage-3.0.77.data/data/lib/portage/bin/dispatch-conf
portage-3.0.77.data/data/lib/portage/bin/emaint
portage-3.0.77.data/data/lib/portage/bin/env-update
portage-3.0.77.data/data/lib/portage/bin/fixpackages
portage-3.0.77.data/data/lib/portage/bin/regenworld
portage-3.0.77.data/data/etc/etc-update.conf
portage-3.0.77.data/data/etc/dispatch-conf.conf
portage-3.0.77.data/data/share/portage/config/make.conf.example
portage-3.0.77.data/data/share/portage/config/make.globals
portage-3.0.77.data/data/share/portage/config/repos.conf
portage-3.0.77.data/data/share/portage/config/repo.postsync.d/example
portage-3.0.77.data/data/share/portage/config/sets/portage.conf
portage-3.0.77.data/data/share/portage/doc/NEWS
portage-3.0.77.data/data/share/portage/doc/RELEASE-NOTES
portage-3.0.77.data/data/lib/portage/bin/bashrc-functions.sh
portage-3.0.77.data/data/lib/portage/bin/binhost-snapshot
portage-3.0.77.data/data/lib/portage/bin/chmod-lite
portage-3.0.77.data/data/lib/portage/bin/chmod-lite.py
portage-3.0.77.data/data/lib/portage/bin/chpathtool.py
portage-3.0.77.data/data/lib/portage/bin/clean_locks
portage-3.0.77.data/data/lib/portage/bin/dohtml.py
portage-3.0.77.data/data/lib/portage/bin/doins.py
portage-3.0.77.data/data/lib/portage/bin/eapi.sh
portage-3.0.77.data/data/lib/portage/bin/ebuild-ipc
portage-3.0.77.data/data/lib/portage/bin/ebuild-ipc.py
portage-3.0.77.data/data/lib/portage/bin/ebuild-pyhelper
portage-3.0.77.data/data/lib/portage/bin/ebuild.sh
portage-3.0.77.data/data/lib/portage/bin/ecompress
portage-3.0.77.dist-info/RECORD
