Metadata-Version: 2.1
Name: portage
Version: 3.0.77
Summary: Portage is the package management and distribution system for Gentoo
Author-Email: Gentoo Portage Development Team <dev-portage@gentoo.org>
License:                     GNU GENERAL PUBLIC LICENSE
Requires-Python: >=3.9
